Workbook

Sheet Dashboard
B2: E-COMMERCE SALES PERFORMANCE — EXECUTIVE DASHBOARD
B3: Data period: 2022–2035 | Source: SalesData table | All figures in USD unless noted
B6: TOTAL REVENUE | G6: TOTAL ORDERS | L6: AVG ORDER VALUE
B7: =Summary!B3 -> 5109775.7 | G7: =Summary!B4 -> 5000 | L7: =Summary!B6 -> 1021.9551
B11: AVG CUSTOMER RATING (/5) | G11: AVG DELIVERY TIME (DAYS) | L11: YoY GROWTH (FY34 vs FY33)
B12: =Summary!B8 -> 2.97398 | G12: =Summary!B9 -> 6.1188 | L12: =Summary!B12 -> -0.11128776
B50: Prepared from SalesData (5,000 orders, Jan 2022–Sep 2035). Revenue figures are net of discounts. Refer to the Summary tab for underlying calculations and the Data tab for the full transaction-level dataset.

Sheet Data
A1: Order ID | B1: Order Date | C1: Customer ID | D1: Product Category | E1: Region | F1: Quantity | G1: Unit Price | H1: Discount | I1: Payment Method | J1: Delivery Days | K1: Customer Rating | L1: Revenue | M1: Gross Revenue | N1: Discount Amount | O1: Order Year | P1: Order Month | Q1: Month Name | R1: Quarter
A2: 10001 | B2: 44562 | C2: 1102 | D2: Beauty | E2: South | F2: 7 | G2: 373.65 | H2: 0.28 | I2: Wallet | J2: 10 | K2: 4.7 | L2: 1883.2 | M2: =F2*G2 -> 2615.55 | N2: =M2-L2 -> 732.35 | O2: =YEAR(B2) -> 2022 | P2: =MONTH(B2) -> 1 | Q2: =TEXT(B2,"mmm") -> Jan | R2: ="Q"&ROUNDUP(MONTH(B2)/3,0) -> Q1
A3: 10002 | B3: 44563 | C3: 1435 | D3: Clothing | E3: South | F3: 7 | G3: 47.74 | H3: 0.09 | I3: Card | J3: 6 | K3: 3.9 | L3: 304.1 | M3: =F3*G3 -> 334.18 | N3: =M3-L3 -> 30.08 | O3: =YEAR(B3) -> 2022 | P3: =MONTH(B3) -> 1 | Q3: =TEXT(B3,"mmm") -> Jan | R3: ="Q"&ROUNDUP(MONTH(B3)/3,0) -> Q1
A4: 10003 | B4: 44564 | C4: 1860 | D4: Beauty | E4: East | F4: 3 | G4: 311.28 | H4: 0.31 | I4: COD | J4: 6 | K4: 2.5 | L4: 644.35 | M4: =F4*G4 -> 933.84 | N4: =M4-L4 -> 289.49 | O4: =YEAR(B4) -> 2022 | P4: =MONTH(B4) -> 1 | Q4: =TEXT(B4,"mmm") -> Jan | R4: ="Q"&ROUNDUP(MONTH(B4)/3,0) -> Q1
A5: 10004 | B5: 44565 | C5: 1270 | D5: Electronics | E5: West | F5: 5 | G5: 524.47 | H5: 0.02 | I5: Wallet | J5: 6 | K5: 1.6 | L5: 2569.9 | M5: =F5*G5 -> 2622.35 | N5: =M5-L5 -> 52.45 | O5: =YEAR(B5) -> 2022 | P5: =MONTH(B5) -> 1 | Q5: =TEXT(B5,"mmm") -> Jan | R5: ="Q"&ROUNDUP(MONTH(B5)/3,0) -> Q1
A6: 10005 | B6: 44566 | C6: 1106 | D6: Clothing | E6: West | F6: 5 | G6: 139.87 | H6: 0.33 | I6: Wallet | J6: 4 | K6: 4.9 | L6: 468.56 | M6: =F6*G6 -> 699.35 | N6: =M6-L6 -> 230.79 | O6: =YEAR(B6) -> 2022 | P6: =MONTH(B6) -> 1 | Q6: =TEXT(B6,"mmm") -> Jan | R6: ="Q"&ROUNDUP(MONTH(B6)/3,0) -> Q1
A7: 10006 | B7: 44567 | C7: 1071 | D7: Electronics | E7: West | F7: 2 | G7: 264.44 | H7: 0.2 | I7: Card | J7: 3 | K7: 3.3 | L7: 423.1 | M7: =F7*G7 -> 528.88 | N7: =M7-L7 -> 105.78 | O7: =YEAR(B7) -> 2022 | P7: =MONTH(B7) -> 1 | Q7: =TEXT(B7,"mmm") -> Jan | R7: ="Q"&ROUNDUP(MONTH(B7)/3,0) -> Q1
A8: 10007 | B8: 44568 | C8: 1700 | D8: Clothing | E8: South | F8: 6 | G8: 564.6 | H8: 0.23 | I8: Card | J8: 1 | K8: 1.8 | L8: 2608.45 | M8: =F8*G8 -> 3387.6 | N8: =M8-L8 -> 779.15 | O8: =YEAR(B8) -> 2022 | P8: =MONTH(B8) -> 1 | Q8: =TEXT(B8,"mmm") -> Jan | R8: ="Q"&ROUNDUP(MONTH(B8)/3,0) -> Q1
A9: 10008 | B9: 44569 | C9: 1020 | D9: Beauty | E9: North | F9: 6 | G9: 265.71 | H9: 0.13 | I9: Card | J9: 2 | K9: 3.7 | L9: 1387.01 | M9: =F9*G9 -> 1594.26 | N9: =M9-L9 -> 207.25 | O9: =YEAR(B9) -> 2022 | P9: =MONTH(B9) -> 1 | Q9: =TEXT(B9,"mmm") -> Jan | R9: ="Q"&ROUNDUP(MONTH(B9)/3,0) -> Q1
A10: 10009 | B10: 44570 | C10: 1614 | D10: Clothing | E10: South | F10: 6 | G10: 224.65 | H10: 0.27 | I10: Card | J10: 2 | K10: 1.4 | L10: 983.97 | M10: =F10*G10 -> 1347.9 | N10: =M10-L10 -> 363.93 | O10: =YEAR(B10) -> 2022 | P10: =MONTH(B10) -> 1 | Q10: =TEXT(B10,"mmm") -> Jan | R10: ="Q"&ROUNDUP(MONTH(B10)/3,0) -> Q1
A11: 10010 | B11: 44571 | C11: 1121 | D11: Clothing | E11: West | F11: 4 | G11: 272.71 | H11: 0.06 | I11: Card | J11: 10 | K11: 4.5 | L11: 1025.39 | M11: =F11*G11 -> 1090.84 | N11: =M11-L11 -> 65.45 | O11: =YEAR(B11) -> 2022 | P11: =MONTH(B11) -> 1 | Q11: =TEXT(B11,"mmm") -> Jan | R11: ="Q"&ROUNDUP(MONTH(B11)/3,0) -> Q1
A12: 10011 | B12: 44572 | C12: 1466 | D12: Clothing | E12: West | F12: 6 | G12: 318.88 | H12: 0.02 | I12: COD | J12: 7 | K12: 1.4 | L12: 1875.01 | M12: =F12*G12 -> 1913.28 | N12: =M12-L12 -> 38.27 | O12: =YEAR(B12) -> 2022 | P12: =MONTH(B12) -> 1 | Q12: =TEXT(B12,"mmm") -> Jan | R12: ="Q"&ROUNDUP(MONTH(B12)/3,0) -> Q1
A13: 10012 | B13: 44573 | C13: 1214 | D13: Electronics | E13: West | F13: 3 | G13: 384.71 | H13: 0.14 | I13: COD | J13: 11 | K13: 1.9 | L13: 992.55 | M13: =F13*G13 -> 1154.13 | N13: =M13-L13 -> 161.58 | O13: =YEAR(B13) -> 2022 | P13: =MONTH(B13) -> 1 | Q13: =TEXT(B13,"mmm") -> Jan | R13: ="Q"&ROUNDUP(MONTH(B13)/3,0) -> Q1
... A5001: 15000 | B5001: 49561 | C5001: 1214 | D5001: Home | E5001: East | F5001: 7 | G5001: 231.58 | H5001: 0.34 | I5001: COD | J5001: 5 | K5001: 3.9 | L5001: 1069.9 | M5001: =F5001*G5001 -> 1621.06 | N5001: =M5001-L5001 -> 551.16 | O5001: =YEAR(B5001) -> 2035 | P5001: =MONTH(B5001) -> 9 | Q5001: =TEXT(B5001,"mmm") -> Sep | R5001: ="Q"&ROUNDUP(MONTH(B5001)/3,0) -> Q3

Sheet Summary
A1: Executive KPI Summary | D1: Revenue by Product Category | H1: Revenue by Region | L1: Revenue by Payment Method
D2: Category | E2: Revenue | F2: Orders | H2: Region | I2: Revenue | J2: Orders | L2: Method | M2: Revenue | N2: Orders
A3: Total Revenue | B3: =SUM(Data!L2:L5001) -> 5109775.7 | D3: Electronics | E3: =SUMIFS(Data!$L$2:$L$5001,Data!$D$2:$D$5001,D3) -> 1829899.2 | F3: =COUNTIFS(Data!$D$2:$D$5001,D3) -> 1777 | H3: North | I3: =SUMIFS(Data!$L$2:$L$5001,Data!$E$2:$E$5001,H3) -> 1281508.4 | J3: =COUNTIFS(Data!$E$2:$E$5001,H3) -> 1276 | L3: Card | M3: =SUMIFS(Data!$L$2:$L$5001,Data!$I$2:$I$5001,L3) -> 2366248.2 | N3: =COUNTIFS(Data!$I$2:$I$5001,L3) -> 2270
A4: Total Orders | B4: =COUNTA(Data!A2:A5001) -> 5000 | D4: Clothing | E4: =SUMIFS(Data!$L$2:$L$5001,Data!$D$2:$D$5001,D4) -> 1531931.7 | F4: =COUNTIFS(Data!$D$2:$D$5001,D4) -> 1531 | H4: South | I4: =SUMIFS(Data!$L$2:$L$5001,Data!$E$2:$E$5001,H4) -> 1246640.9 | J4: =COUNTIFS(Data!$E$2:$E$5001,H4) -> 1208 | L4: COD | M4: =SUMIFS(Data!$L$2:$L$5001,Data!$I$2:$I$5001,L4) -> 1788408.4 | N4: =COUNTIFS(Data!$I$2:$I$5001,L4) -> 1774
A5: Total Units Sold | B5: =SUM(Data!F2:F5001) -> 20224 | D5: Home | E5: =SUMIFS(Data!$L$2:$L$5001,Data!$D$2:$D$5001,D5) -> 982083.92 | F5: =COUNTIFS(Data!$D$2:$D$5001,D5) -> 969 | H5: East | I5: =SUMIFS(Data!$L$2:$L$5001,Data!$E$2:$E$5001,H5) -> 1236044.2 | J5: =COUNTIFS(Data!$E$2:$E$5001,H5) -> 1227 | L5: Wallet | M5: =SUMIFS(Data!$L$2:$L$5001,Data!$I$2:$I$5001,L5) -> 955119.1 | N5: =COUNTIFS(Data!$I$2:$I$5001,L5) -> 956
A6: Average Order Value | B6: =B3/B4 -> 1021.9551 | D6: Beauty | E6: =SUMIFS(Data!$L$2:$L$5001,Data!$D$2:$D$5001,D6) -> 765860.88 | F6: =COUNTIFS(Data!$D$2:$D$5001,D6) -> 723 | H6: West | I6: =SUMIFS(Data!$L$2:$L$5001,Data!$E$2:$E$5001,H6) -> 1345582.2 | J6: =COUNTIFS(Data!$E$2:$E$5001,H6) -> 1289
A7: Average Discount Rate | B7: =AVERAGE(Data!H2:H5001) -> 0.179984
A8: Average Customer Rating | B8: =AVERAGE(Data!K2:K5001) -> 2.97398
A9: Average Delivery Days (days) | B9: =AVERAGE(Data!J2:J5001) -> 6.1188
A10: Latest Full Year Revenue | B10: =SUMIFS(Data!L2:L5001,Data!O2:O5001,2034) -> 363239.55
A11: Prior Full Year Revenue | B11: =SUMIFS(Data!L2:L5001,Data!O2:O5001,2033) -> 408725.72
A12: YoY Growth % | B12: =(B10-B11)/B11 -> -0.11128776
A15: Revenue Trend by Year | E15: Seasonality: Revenue by Month | I15: Service Quality Metrics
A16: Year | B16: Revenue | C16: Orders | E16: Month | F16: Revenue | G16: Orders | I16: Category | J16: Avg Rating | K16: Region | L16: Avg Delivery (days)
A17: 2022 | B17: =SUMIFS(Data!$L$2:$L$5001,Data!$O$2:$O$5001,A17) -> 371824.3 | C17: =COUNTIFS(Data!$O$2:$O$5001,A17) -> 365 | E17: Jan | F17: =SUMIFS(Data!$L$2:$L$5001,Data!$P$2:$P$5001,1) -> 426374.92 | G17: =COUNTIFS(Data!$P$2:$P$5001,1) -> 434 | I17: Electronics | J17: =AVERAGEIFS(Data!$K$2:$K$5001,Data!$D$2:$D$5001,I17) -> 2.9510974 | K17: North | L17: =AVERAGEIFS(Data!$J$2:$J$5001,Data!$E$2:$E$5001,K17) -> 6.1183386
A18: 2023 | B18: =SUMIFS(Data!$L$2:$L$5001,Data!$O$2:$O$5001,A18) -> 365915.79 | C18: =COUNTIFS(Data!$O$2:$O$5001,A18) -> 365 | E18: Feb | F18: =SUMIFS(Data!$L$2:$L$5001,Data!$P$2:$P$5001,2) -> 413890.24 | G18: =COUNTIFS(Data!$P$2:$P$5001,2) -> 395 | I18: Clothing | J18: =AVERAGEIFS(Data!$K$2:$K$5001,Data!$D$2:$D$5001,I18) -> 3.0050947 | K18: South | L18: =AVERAGEIFS(Data!$J$2:$J$5001,Data!$E$2:$E$5001,K18) -> 6.1730132
A19: 2024 | B19: =SUMIFS(Data!$L$2:$L$5001,Data!$O$2:$O$5001,A19) -> 363209.13 | C19: =COUNTIFS(Data!$O$2:$O$5001,A19) -> 366 | E19: Mar | F19: =SUMIFS(Data!$L$2:$L$5001,Data!$P$2:$P$5001,3) -> 425050.52 | G19: =COUNTIFS(Data!$P$2:$P$5001,3) -> 434 | I19: Home | J19: =AVERAGEIFS(Data!$K$2:$K$5001,Data!$D$2:$D$5001,I19) -> 2.9406605 | K19: East | L19: =AVERAGEIFS(Data!$J$2:$J$5001,Data!$E$2:$E$5001,K19) -> 6.1043195
A20: 2025 | B20: =SUMIFS(Data!$L$2:$L$5001,Data!$O$2:$O$5001,A20) -> 349802.33 | C20: =COUNTIFS(Data!$O$2:$O$5001,A20) -> 365 | E20: Apr | F20: =SUMIFS(Data!$L$2:$L$5001,Data!$P$2:$P$5001,4) -> 398715.16 | G20: =COUNTIFS(Data!$P$2:$P$5001,4) -> 420 | I20: Beauty | J20: =AVERAGEIFS(Data!$K$2:$K$5001,Data!$D$2:$D$5001,I20) -> 3.0089903 | K20: West | L20: =AVERAGEIFS(Data!$J$2:$J$5001,Data!$E$2:$E$5001,K20) -> 6.0822343
A21: 2026 | B21: =SUMIFS(Data!$L$2:$L$5001,Data!$O$2:$O$5001,A21) -> 386369.69 | C21: =COUNTIFS(Data!$O$2:$O$5001,A21) -> 365 | E21: May | F21: =SUMIFS(Data!$L$2:$L$5001,Data!$P$2:$P$5001,5) -> 479772.55 | G21: =COUNTIFS(Data!$P$2:$P$5001,5) -> 434
A22: 2027 | B22: =SUMIFS(Data!$L$2:$L$5001,Data!$O$2:$O$5001,A22) -> 386151.91 | C22: =COUNTIFS(Data!$O$2:$O$5001,A22) -> 365 | E22: Jun | F22: =SUMIFS(Data!$L$2:$L$5001,Data!$P$2:$P$5001,6) -> 442941.58 | G22: =COUNTIFS(Data!$P$2:$P$5001,6) -> 420
A23: 2028 | B23: =SUMIFS(Data!$L$2:$L$5001,Data!$O$2:$O$5001,A23) -> 376844.8 | C23: =COUNTIFS(Data!$O$2:$O$5001,A23) -> 366 | E23: Jul | F23: =SUMIFS(Data!$L$2:$L$5001,Data!$P$2:$P$5001,7) -> 440570.72 | G23: =COUNTIFS(Data!$P$2:$P$5001,7) -> 434
A24: 2029 | B24: =SUMIFS(Data!$L$2:$L$5001,Data!$O$2:$O$5001,A24) -> 359239.24 | C24: =COUNTIFS(Data!$O$2:$O$5001,A24) -> 365 | E24: Aug | F24: =SUMIFS(Data!$L$2:$L$5001,Data!$P$2:$P$5001,8) -> 460874.78 | G24: =COUNTIFS(Data!$P$2:$P$5001,8) -> 434
A25: 2030 | B25: =SUMIFS(Data!$L$2:$L$5001,Data!$O$2:$O$5001,A25) -> 387884.46 | C25: =COUNTIFS(Data!$O$2:$O$5001,A25) -> 365 | E25: Sep | F25: =SUMIFS(Data!$L$2:$L$5001,Data!$P$2:$P$5001,9) -> 402368.11 | G25: =COUNTIFS(Data!$P$2:$P$5001,9) -> 399
A26: 2031 | B26: =SUMIFS(Data!$L$2:$L$5001,Data!$O$2:$O$5001,A26) -> 365250.83 | C26: =COUNTIFS(Data!$O$2:$O$5001,A26) -> 365 | E26: Oct | F26: =SUMIFS(Data!$L$2:$L$5001,Data!$P$2:$P$5001,10) -> 407873.12 | G26: =COUNTIFS(Data!$P$2:$P$5001,10) -> 403
A27: 2032 | B27: =SUMIFS(Data!$L$2:$L$5001,Data!$O$2:$O$5001,A27) -> 386584.63 | C27: =COUNTIFS(Data!$O$2:$O$5001,A27) -> 366 | E27: Nov | F27: =SUMIFS(Data!$L$2:$L$5001,Data!$P$2:$P$5001,11) -> 410657.88 | G27: =COUNTIFS(Data!$P$2:$P$5001,11) -> 390
A28: 2033 | B28: =SUMIFS(Data!$L$2:$L$5001,Data!$O$2:$O$5001,A28) -> 408725.72 | C28: =COUNTIFS(Data!$O$2:$O$5001,A28) -> 365 | E28: Dec | F28: =SUMIFS(Data!$L$2:$L$5001,Data!$P$2:$P$5001,12) -> 400686.16 | G28: =COUNTIFS(Data!$P$2:$P$5001,12) -> 403
A29: 2034 | B29: =SUMIFS(Data!$L$2:$L$5001,Data!$O$2:$O$5001,A29) -> 363239.55 | C29: =COUNTIFS(Data!$O$2:$O$5001,A29) -> 365
A30: 2035 | B30: =SUMIFS(Data!$L$2:$L$5001,Data!$O$2:$O$5001,A30) -> 238733.36 | C30: =COUNTIFS(Data!$O$2:$O$5001,A30) -> 252
