Workbook

Sheet Executive Summary
B2: Indian Overseas Migration Analytics
B3: Executive Summary | Coverage: 2000-2024 | 7 Destination Countries
B5: Total Records | E5: Countries Covered | H5: Latest Year (Migrant Stock Data) | K5: Total Migrants Tracked, 2024 | N5: India GDP 2024 ($B) | Q5: Remittances 2024 ($B)
B6: =COUNTA('Migration Data'!A2:A183) -> 182 | E6: =SUMPRODUCT(1/COUNTIF('Migration Data'!B2:B183,'Migration Data'!B2:B183)) -> 7 | H6: =_xlfn.MAXIFS('Migration Data'!A2:A183,'Migration Data'!I2:I183,"<>") -> 2024 | K6: =SUMIFS('Migration Data'!I2:I183,'Migration Data'!A2:A183,2024) -> 10266000 | N6: =AVERAGEIFS('Migration Data'!D2:D183,'Migration Data'!A2:A183,2024) -> 3910 | Q6: =AVERAGEIFS('Migration Data'!F2:F183,'Migration Data'!A2:A183,2024) -> 137.67
B9: Headline Takeaways
B10: - UAE (3.25M) and USA (3.17M) are the largest tracked Indian migrant destinations as of 2024.
B11: - Canada is the fastest-growing corridor: +490% since 2000 (217K -> 1.28M).
B12: - UK growth lagged all tracked countries: only +70% since 2000, likely tied to post-Brexit visa tightening.
B13: - Remittances to India grew ~10.7x (2000-2024), tracking India's GDP (r=0.98) far more than migrant headcount.
B14: - India's GDP grew 8.3x over the same period with no corresponding slowdown in emigration.
B15: - Workforce/student composition data is too sparse (2 of 182 records) to support a general trend claim.
B17: Note: migrant-stock figures are recorded only in benchmark years (2000, 2005/2010, 2015, 2020, 2024). GDP, unemployment, and remittances are India-wide national figures repeated across countries, not country-specific. See 'Data Quality Report' tab for full detail.
B20: Chart Data (helper table - formulas pull from Migration Data)
B21: Country | C21: Migrants (2024)
B22: Australia | C22: =SUMIFS('Migration Data'!I2:I183,'Migration Data'!A2:A183,2024,'Migration Data'!B2:B183,"Australia") -> 916000
B23: Canada | C23: =SUMIFS('Migration Data'!I2:I183,'Migration Data'!A2:A183,2024,'Migration Data'!B2:B183,"Canada") -> 1280000
B24: Germany | C24: =SUMIFS('Migration Data'!I2:I183,'Migration Data'!A2:A183,2024,'Migration Data'!B2:B183,"Germany") -> 285000
B25: Singapore | C25: =SUMIFS('Migration Data'!I2:I183,'Migration Data'!A2:A183,2024,'Migration Data'!B2:B183,"Singapore") -> 395000
B26: UAE | C26: =SUMIFS('Migration Data'!I2:I183,'Migration Data'!A2:A183,2024,'Migration Data'!B2:B183,"UAE") -> 3250000
B27: UK | C27: =SUMIFS('Migration Data'!I2:I183,'Migration Data'!A2:A183,2024,'Migration Data'!B2:B183,"UK") -> 970000
B28: USA | C28: =SUMIFS('Migration Data'!I2:I183,'Migration Data'!A2:A183,2024,'Migration Data'!B2:B183,"USA") -> 3170000
B31: Year | C31: India GDP ($B) | D31: Remittances ($B)
B32: 2000 | C32: =AVERAGEIFS('Migration Data'!D2:D183,'Migration Data'!A2:A183,2000) -> 468.4 | D32: =AVERAGEIFS('Migration Data'!F2:F183,'Migration Data'!A2:A183,2000) -> 12.88
B33: 2001 | C33: =AVERAGEIFS('Migration Data'!D2:D183,'Migration Data'!A2:A183,2001) -> 485.44 | D33: =AVERAGEIFS('Migration Data'!F2:F183,'Migration Data'!A2:A183,2001) -> 14.27
B34: 2002 | C34: =AVERAGEIFS('Migration Data'!D2:D183,'Migration Data'!A2:A183,2002) -> 514.94 | D34: =AVERAGEIFS('Migration Data'!F2:F183,'Migration Data'!A2:A183,2002) -> 15.74
B35: 2003 | C35: =AVERAGEIFS('Migration Data'!D2:D183,'Migration Data'!A2:A183,2003) -> 607.7 | D35: =AVERAGEIFS('Migration Data'!F2:F183,'Migration Data'!A2:A183,2003) -> 21
B36: 2004 | C36: =AVERAGEIFS('Migration Data'!D2:D183,'Migration Data'!A2:A183,2004) -> 709.15 | D36: =AVERAGEIFS('Migration Data'!F2:F183,'Migration Data'!A2:A183,2004) -> 18.75
B37: 2005 | C37: =AVERAGEIFS('Migration Data'!D2:D183,'Migration Data'!A2:A183,2005) -> 820.38 | D37: =AVERAGEIFS('Migration Data'!F2:F183,'Migration Data'!A2:A183,2005) -> 22.13
B38: 2006 | C38: =AVERAGEIFS('Migration Data'!D2:D183,'Migration Data'!A2:A183,2006) -> 940.26 | D38: =AVERAGEIFS('Migration Data'!F2:F183,'Migration Data'!A2:A183,2006) -> 28.33
B39: 2007 | C39: =AVERAGEIFS('Migration Data'!D2:D183,'Migration Data'!A2:A183,2007) -> 1217 | D39: =AVERAGEIFS('Migration Data'!F2:F183,'Migration Data'!A2:A183,2007) -> 37.22
B40: 2008 | C40: =AVERAGEIFS('Migration Data'!D2:D183,'Migration Data'!A2:A183,2008) -> 1199 | D40: =AVERAGEIFS('Migration Data'!F2:F183,'Migration Data'!A2:A183,2008) -> 49.98
B41: 2009 | C41: =AVERAGEIFS('Migration Data'!D2:D183,'Migration Data'!A2:A183,2009) -> 1342 | D41: =AVERAGEIFS('Migration Data'!F2:F183,'Migration Data'!A2:A183,2009) -> 49.2
B42: 2010 | C42: =AVERAGEIFS('Migration Data'!D2:D183,'Migration Data'!A2:A183,2010) -> 1676 | D42: =AVERAGEIFS('Migration Data'!F2:F183,'Migration Data'!A2:A183,2010) -> 53.48
B43: 2011 | C43: =AVERAGEIFS('Migration Data'!D2:D183,'Migration Data'!A2:A183,2011) -> 1823 | D43: =AVERAGEIFS('Migration Data'!F2:F183,'Migration Data'!A2:A183,2011) -> 62.5
B44: 2012 | C44: =AVERAGEIFS('Migration Data'!D2:D183,'Migration Data'!A2:A183,2012) -> 1828 | D44: =AVERAGEIFS('Migration Data'!F2:F183,'Migration Data'!A2:A183,2012) -> 68.82
B45: 2013 | C45: =AVERAGEIFS('Migration Data'!D2:D183,'Migration Data'!A2:A183,2013) -> 1857 | D45: =AVERAGEIFS('Migration Data'!F2:F183,'Migration Data'!A2:A183,2013) -> 69.97
B46: 2014 | C46: =AVERAGEIFS('Migration Data'!D2:D183,'Migration Data'!A2:A183,2014) -> 2039 | D46: =AVERAGEIFS('Migration Data'!F2:F183,'Migration Data'!A2:A183,2014) -> 70.39
B47: 2015 | C47: =AVERAGEIFS('Migration Data'!D2:D183,'Migration Data'!A2:A183,2015) -> 2104 | D47: =AVERAGEIFS('Migration Data'!F2:F183,'Migration Data'!A2:A183,2015) -> 68.91
B48: 2016 | C48: =AVERAGEIFS('Migration Data'!D2:D183,'Migration Data'!A2:A183,2016) -> 2295 | D48: =AVERAGEIFS('Migration Data'!F2:F183,'Migration Data'!A2:A183,2016) -> 62.74
B49: 2017 | C49: =AVERAGEIFS('Migration Data'!D2:D183,'Migration Data'!A2:A183,2017) -> 2651 | D49: =AVERAGEIFS('Migration Data'!F2:F183,'Migration Data'!A2:A183,2017) -> 68.97
B50: 2018 | C50: =AVERAGEIFS('Migration Data'!D2:D183,'Migration Data'!A2:A183,2018) -> 2703 | D50: =AVERAGEIFS('Migration Data'!F2:F183,'Migration Data'!A2:A183,2018) -> 78.79
B51: 2019 | C51: =AVERAGEIFS('Migration Data'!D2:D183,'Migration Data'!A2:A183,2019) -> 2836 | D51: =AVERAGEIFS('Migration Data'!F2:F183,'Migration Data'!A2:A183,2019) -> 83.33
B52: 2020 | C52: =AVERAGEIFS('Migration Data'!D2:D183,'Migration Data'!A2:A183,2020) -> 2675 | D52: =AVERAGEIFS('Migration Data'!F2:F183,'Migration Data'!A2:A183,2020) -> 83.15
B53: 2021 | C53: =AVERAGEIFS('Migration Data'!D2:D183,'Migration Data'!A2:A183,2021) -> 3167 | D53: =AVERAGEIFS('Migration Data'!F2:F183,'Migration Data'!A2:A183,2021) -> 89.38
B54: 2022 | C54: =AVERAGEIFS('Migration Data'!D2:D183,'Migration Data'!A2:A183,2022) -> 3346 | D54: =AVERAGEIFS('Migration Data'!F2:F183,'Migration Data'!A2:A183,2022) -> 111.22
B55: 2023 | C55: =AVERAGEIFS('Migration Data'!D2:D183,'Migration Data'!A2:A183,2023) -> 3638 | D55: =AVERAGEIFS('Migration Data'!F2:F183,'Migration Data'!A2:A183,2023) -> 119.53
B56: 2024 | C56: =AVERAGEIFS('Migration Data'!D2:D183,'Migration Data'!A2:A183,2024) -> 3910 | D56: =AVERAGEIFS('Migration Data'!F2:F183,'Migration Data'!A2:A183,2024) -> 137.67

Sheet Migration Data
A1: Year | B1: Destination Country | C1: Region | D1: GDP India USD Billion | E1: Permanent Migrants | F1: Remittance USD Billion | G1: Students | H1: Temporary Workers | I1: Total Indian Migrants | J1: Unemployment India | K1: Destination Country Full | L1: Migrant YoY Growth Pct | M1: Temporary Worker Share Pct | N1: Student Share Pct | O1: Remittance per Migrant USD Th | P1: Migrant 3yr Moving Avg | Q1: High Migration Flag | R1: India Unemployment Category
A2: 2000 | B2: Australia | C2: Oceania | D2: 468.4 | F2: 12.88 | I2: 173000 | J2: 7.62 | K2: Australia | O2: 74.450867 | P2: 173000 | Q2: Normal | R2: Moderate (6-8%)
A3: 2001 | B3: Australia | C3: Oceania | D3: 485.44 | F3: 14.27 | J3: 7.61 | K3: Australia | P3: 173000 | Q3: Normal | R3: Moderate (6-8%)
A4: 2002 | B4: Australia | C4: Oceania | D4: 514.94 | F4: 15.74 | J4: 7.68 | K4: Australia | P4: 173000 | Q4: Normal | R4: Moderate (6-8%)
A5: 2003 | B5: Australia | C5: Oceania | D5: 607.7 | F5: 21 | J5: 7.63 | K5: Australia | Q5: Normal | R5: Moderate (6-8%)
A6: 2004 | B6: Australia | C6: Oceania | D6: 709.15 | F6: 18.75 | J6: 7.6 | K6: Australia | Q6: Normal | R6: Moderate (6-8%)
A7: 2005 | B7: Australia | C7: Oceania | D7: 820.38 | F7: 22.13 | J7: 7.55 | K7: Australia | Q7: Normal | R7: Moderate (6-8%)
A8: 2006 | B8: Australia | C8: Oceania | D8: 940.26 | F8: 28.33 | J8: 7.55 | K8: Australia | Q8: Normal | R8: Moderate (6-8%)
A9: 2007 | B9: Australia | C9: Oceania | D9: 1217 | F9: 37.22 | J9: 7.56 | K9: Australia | Q9: Normal | R9: Moderate (6-8%)
A10: 2008 | B10: Australia | C10: Oceania | D10: 1199 | F10: 49.98 | J10: 7.63 | K10: Australia | Q10: Normal | R10: Moderate (6-8%)
A11: 2009 | B11: Australia | C11: Oceania | D11: 1342 | F11: 49.2 | J11: 7.64 | K11: Australia | Q11: Normal | R11: Moderate (6-8%)
A12: 2010 | B12: Australia | C12: Oceania | D12: 1676 | E12: 17000 | F12: 53.48 | I12: 330000 | J12: 7.63 | K12: Australia | O12: 162.06061 | P12: 330000 | Q12: Normal | R12: Moderate (6-8%)
A13: 2011 | B13: Australia | C13: Oceania | D13: 1823 | F13: 62.5 | J13: 7.61 | K13: Australia | P13: 330000 | Q13: Normal | R13: Moderate (6-8%)
A14: 2012 | B14: Australia | C14: Oceania | D14: 1828 | F14: 68.82 | J14: 7.64 | K14: Australia | P14: 330000 | Q14: Normal | R14: Moderate (6-8%)
A15: 2013 | B15: Australia | C15: Oceania | D15: 1857 | F15: 69.97 | J15: 7.68 | K15: Australia | Q15: Normal | R15: Moderate (6-8%)
A16: 2014 | B16: Australia | C16: Oceania | D16: 2039 | F16: 70.39 | J16: 7.66 | K16: Australia | Q16: Normal | R16: Moderate (6-8%)
A17: 2015 | B17: Australia | C17: Oceania | D17: 2104 | F17: 68.91 | I17: 448000 | J17: 7.63 | K17: Australia | O17: 153.81696 | P17: 448000 | Q17: Normal | R17: Moderate (6-8%)
A18: 2016 | B18: Australia | C18: Oceania | D18: 2295 | F18: 62.74 | J18: 7.61 | K18: Australia | P18: 448000 | Q18: Normal | R18: Moderate (6-8%)
A19: 2017 | B19: Australia | C19: Oceania | D19: 2651 | E19: 33310 | F19: 68.97 | G19: 49469 | H19: 16124 | J19: 7.63 | K19: Australia | P19: 448000 | Q19: Normal | R19: Moderate (6-8%)
A20: 2018 | B20: Australia | C20: Oceania | D20: 2703 | E20: 33611 | F20: 78.79 | G20: 66449 | H20: 22357 | J20: 7.65 | K20: Australia | Q20: Normal | R20: Moderate (6-8%)
A21: 2019 | B21: Australia | C21: Oceania | D21: 2836 | E21: 25698 | F21: 83.33 | G21: 55560 | H21: 13434 | J21: 6.51 | K21: Australia | Q21: Normal | R21: Moderate (6-8%)
A22: 2020 | B22: Australia | C22: Oceania | D22: 2675 | E22: 21791 | F22: 83.15 | G22: 47031 | H22: 10071 | I22: 721000 | J22: 7.86 | K22: Australia | M22: 1.39681 | N22: 6.5230236 | O22: 115.32594 | P22: 721000 | Q22: High | R22: Moderate (6-8%)
A23: 2021 | B23: Australia | C23: Oceania | D23: 3167 | E23: 24324 | F23: 89.38 | G23: 200325 | H23: 18717 | J23: 6.38 | K23: Australia | P23: 721000 | Q23: Normal | R23: Moderate (6-8%)
A24: 2022 | B24: Australia | C24: Oceania | D24: 3346 | E24: 41145 | F24: 111.22 | G24: 357038 | H24: 27402 | J24: 4.82 | K24: Australia | P24: 721000 | Q24: Normal | R24: Low (<6%)
A25: 2023 | B25: Australia | C25: Oceania | D25: 3638 | F25: 119.53 | G25: 287259 | J25: 4.17 | K25: Australia | Q25: Normal | R25: Low (<6%)
A26: 2024 | B26: Australia | C26: Oceania | D26: 3910 | F26: 137.67 | G26: 302758 | I26: 916000 | J26: 4.17 | K26: Australia | N26: 33.052183 | O26: 150.29476 | P26: 916000 | Q26: High | R26: Low (<6%)
A27: 2025 | B27: Australia | C27: Oceania | J27: 4.22 | K27: Australia | P27: 916000 | Q27: Normal | R27: Low (<6%)
A28: 2000 | B28: Canada | C28: North America | D28: 468.4 | E28: 26122 | F28: 12.88 | I28: 217000 | J28: 7.62 | K28: Canada | O28: 59.354839 | P28: 217000 | Q28: Normal | R28: Moderate (6-8%)
A29: 2001 | B29: Canada | C29: North America | D29: 485.44 | F29: 14.27 | J29: 7.61 | K29: Canada | P29: 217000 | Q29: Normal | R29: Moderate (6-8%)
A30: 2002 | B30: Canada | C30: North America | D30: 514.94 | F30: 15.74 | J30: 7.68 | K30: Canada | P30: 217000 | Q30: Normal | R30: Moderate (6-8%)
A31: 2003 | B31: Canada | C31: North America | D31: 607.7 | F31: 21 | J31: 7.63 | K31: Canada | Q31: Normal | R31: Moderate (6-8%)
A32: 2004 | B32: Canada | C32: North America | D32: 709.15 | F32: 18.75 | J32: 7.6 | K32: Canada | Q32: Normal | R32: Moderate (6-8%)
A33: 2005 | B33: Canada | C33: North America | D33: 820.38 | F33: 22.13 | J33: 7.55 | K33: Canada | Q33: Normal | R33: Moderate (6-8%)
A34: 2006 | B34: Canada | C34: North America | D34: 940.26 | F34: 28.33 | J34: 7.55 | K34: Canada | Q34: Normal | R34: Moderate (6-8%)
A35: 2007 | B35: Canada | C35: North America | D35: 1217 | F35: 37.22 | J35: 7.56 | K35: Canada | Q35: Normal | R35: Moderate (6-8%)
A36: 2008 | B36: Canada | C36: North America | D36: 1199 | F36: 49.98 | J36: 7.63 | K36: Canada | Q36: Normal | R36: Moderate (6-8%)
A37: 2009 | B37: Canada | C37: North America | D37: 1342 | F37: 49.2 | J37: 7.64 | K37: Canada | Q37: Normal | R37: Moderate (6-8%)
A38: 2010 | B38: Canada | C38: North America | D38: 1676 | E38: 30311 | F38: 53.48 | I38: 540000 | J38: 7.63 | K38: Canada | O38: 99.037037 | P38: 540000 | Q38: Normal | R38: Moderate (6-8%)
A39: 2011 | B39: Canada | C39: North America | D39: 1823 | F39: 62.5 | J39: 7.61 | K39: Canada | P39: 540000 | Q39: Normal | R39: Moderate (6-8%)
A40: 2012 | B40: Canada | C40: North America | D40: 1828 | F40: 68.82 | J40: 7.64 | K40: Canada | P40: 540000 | Q40: Normal | R40: Moderate (6-8%)
A41: 2013 | B41: Canada | C41: North America | D41: 1857 | F41: 69.97 | J41: 7.68 | K41: Canada | Q41: Normal | R41: Moderate (6-8%)
A42: 2014 | B42: Canada | C42: North America | D42: 2039 | F42: 70.39 | J42: 7.66 | K42: Canada | Q42: Normal | R42: Moderate (6-8%)
A43: 2015 | B43: Canada | C43: North America | D43: 2104 | E43: 39340 | F43: 68.91 | G43: 172600 | I43: 710000 | J43: 7.63 | K43: Canada | N43: 24.309859 | O43: 97.056338 | P43: 710000 | Q43: Normal | R43: Moderate (6-8%)
A44: 2016 | B44: Canada | C44: North America | D44: 2295 | F44: 62.74 | J44: 7.61 | K44: Canada | P44: 710000 | Q44: Normal | R44: Moderate (6-8%)
A45: 2017 | B45: Canada | C45: North America | D45: 2651 | F45: 68.97 | J45: 7.63 | K45: Canada | P45: 710000 | Q45: Normal | R45: Moderate (6-8%)
A46: 2018 | B46: Canada | C46: North America | D46: 2703 | E46: 69985 | F46: 78.79 | J46: 7.65 | K46: Canada | Q46: Normal | R46: Moderate (6-8%)
A47: 2019 | B47: Canada | C47: North America | D47: 2836 | E47: 85590 | F47: 83.33 | J47: 6.51 | K47: Canada | Q47: Normal | R47: Moderate (6-8%)
A48: 2020 | B48: Canada | C48: North America | D48: 2675 | E48: 42875 | F48: 83.15 | I48: 1020000 | J48: 7.86 | K48: Canada | O48: 81.519608 | P48: 1020000 | Q48: High | R48: Moderate (6-8%)
A49: 2021 | B49: Canada | C49: North America | D49: 3167 | E49: 127945 | F49: 89.38 | J49: 6.38 | K49: Canada | P49: 1020000 | Q49: Normal | R49: Moderate (6-8%)
A50: 2022 | B50: Canada | C50: North America | D50: 3346 | E50: 118250 | F50: 111.22 | J50: 4.82 | K50: Canada | P50: 1020000 | Q50: Normal | R50: Low (<6%)
A51: 2023 | B51: Canada | C51: North America | D51: 3638 | E51: 139790 | F51: 119.53 | G51: 427000 | J51: 4.17 | K51: Canada | Q51: Normal | R51: Low (<6%)
A52: 2024 | B52: Canada | C52: North America | D52: 3910 | E52: 127375 | F52: 137.67 | I52: 1280000 | J52: 4.17 | K52: Canada | O52: 107.55469 | P52: 1280000 | Q52: High | R52: Low (<6%)
A53: 2025 | B53: Canada | C53: North America | E53: 98825 | J53: 4.22 | K53: Canada | P53: 1280000 | Q53: Normal | R53: Low (<6%)
A54: 2000 | B54: Germany | C54: Europe | D54: 468.4 | F54: 12.88 | J54: 7.62 | K54: Germany | Q54: Normal | R54: Moderate (6-8%)
A55: 2001 | B55: Germany | C55: Europe | D55: 485.44 | F55: 14.27 | J55: 7.61 | K55: Germany | Q55: Normal | R55: Moderate (6-8%)
A56: 2002 | B56: Germany | C56: Europe | D56: 514.94 | F56: 15.74 | J56: 7.68 | K56: Germany | Q56: Normal | R56: Moderate (6-8%)
A57: 2003 | B57: Germany | C57: Europe | D57: 607.7 | F57: 21 | J57: 7.63 | K57: Germany | Q57: Normal | R57: Moderate (6-8%)
A58: 2004 | B58: Germany | C58: Europe | D58: 709.15 | F58: 18.75 | J58: 7.6 | K58: Germany | Q58: Normal | R58: Moderate (6-8%)
A59: 2005 | B59: Germany | C59: Europe | D59: 820.38 | F59: 22.13 | J59: 7.55 | K59: Germany | Q59: Normal | R59: Moderate (6-8%)
A60: 2006 | B60: Germany | C60: Europe | D60: 940.26 | F60: 28.33 | J60: 7.55 | K60: Germany | Q60: Normal | R60: Moderate (6-8%)
A61: 2007 | B61: Germany | C61: Europe | D61: 1217 | F61: 37.22 | J61: 7.56 | K61: Germany | Q61: Normal | R61: Moderate (6-8%)
A62: 2008 | B62: Germany | C62: Europe | D62: 1199 | F62: 49.98 | J62: 7.63 | K62: Germany | Q62: Normal | R62: Moderate (6-8%)
A63: 2009 | B63: Germany | C63: Europe | D63: 1342 | F63: 49.2 | J63: 7.64 | K63: Germany | Q63: Normal | R63: Moderate (6-8%)
A64: 2010 | B64: Germany | C64: Europe | D64: 1676 | F64: 53.48 | I64: 60000 | J64: 7.63 | K64: Germany | O64: 891.33333 | P64: 60000 | Q64: Normal | R64: Moderate (6-8%)
A65: 2011 | B65: Germany | C65: Europe | D65: 1823 | F65: 62.5 | J65: 7.61 | K65: Germany | P65: 60000 | Q65: Normal | R65: Moderate (6-8%)
A66: 2012 | B66: Germany | C66: Europe | D66: 1828 | F66: 68.82 | J66: 7.64 | K66: Germany | P66: 60000 | Q66: Normal | R66: Moderate (6-8%)
A67: 2013 | B67: Germany | C67: Europe | D67: 1857 | F67: 69.97 | J67: 7.68 | K67: Germany | Q67: Normal | R67: Moderate (6-8%)
A68: 2014 | B68: Germany | C68: Europe | D68: 2039 | F68: 70.39 | J68: 7.66 | K68: Germany | Q68: Normal | R68: Moderate (6-8%)
A69: 2015 | B69: Germany | C69: Europe | D69: 2104 | F69: 68.91 | I69: 98000 | J69: 7.63 | K69: Germany | O69: 703.16327 | P69: 98000 | Q69: Normal | R69: Moderate (6-8%)
A70: 2016 | B70: Germany | C70: Europe | D70: 2295 | F70: 62.74 | J70: 7.61 | K70: Germany | P70: 98000 | Q70: Normal | R70: Moderate (6-8%)
A71: 2017 | B71: Germany | C71: Europe | D71: 2651 | F71: 68.97 | J71: 7.63 | K71: Germany | P71: 98000 | Q71: Normal | R71: Moderate (6-8%)
A72: 2018 | B72: Germany | C72: Europe | D72: 2703 | F72: 78.79 | J72: 7.65 | K72: Germany | Q72: Normal | R72: Moderate (6-8%)
A73: 2019 | B73: Germany | C73: Europe | D73: 2836 | F73: 83.33 | J73: 6.51 | K73: Germany | Q73: Normal | R73: Moderate (6-8%)
A74: 2020 | B74: Germany | C74: Europe | D74: 2675 | F74: 83.15 | G74: 28905 | I74: 210000 | J74: 7.86 | K74: Germany | N74: 13.764286 | O74: 395.95238 | P74: 210000 | Q74: Normal | R74: Moderate (6-8%)
A75: 2021 | B75: Germany | C75: Europe | D75: 3167 | F75: 89.38 | J75: 6.38 | K75: Germany | P75: 210000 | Q75: Normal | R75: Moderate (6-8%)
A76: 2022 | B76: Germany | C76: Europe | D76: 3346 | F76: 111.22 | J76: 4.82 | K76: Germany | P76: 210000 | Q76: Normal | R76: Low (<6%)
A77: 2023 | B77: Germany | C77: Europe | D77: 3638 | F77: 119.53 | J77: 4.17 | K77: Germany | Q77: Normal | R77: Low (<6%)
A78: 2024 | B78: Germany | C78: Europe | D78: 3910 | F78: 137.67 | I78: 285000 | J78: 4.17 | K78: Germany | O78: 483.05263 | P78: 285000 | Q78: High | R78: Low (<6%)
A79: 2025 | B79: Germany | C79: Europe | G79: 60000 | J79: 4.22 | K79: Germany | P79: 285000 | Q79: Normal | R79: Low (<6%)
A80: 2000 | B80: Singapore | C80: Asia | D80: 468.4 | F80: 12.88 | I80: 85000 | J80: 7.62 | K80: Singapore | O80: 151.52941 | P80: 85000 | Q80: Normal | R80: Moderate (6-8%)
A81: 2001 | B81: Singapore | C81: Asia | D81: 485.44 | F81: 14.27 | J81: 7.61 | K81: Singapore | P81: 85000 | Q81: Normal | R81: Moderate (6-8%)
A82: 2002 | B82: Singapore | C82: Asia | D82: 514.94 | F82: 15.74 | J82: 7.68 | K82: Singapore | P82: 85000 | Q82: Normal | R82: Moderate (6-8%)
A83: 2003 | B83: Singapore | C83: Asia | D83: 607.7 | F83: 21 | J83: 7.63 | K83: Singapore | Q83: Normal | R83: Moderate (6-8%)
A84: 2004 | B84: Singapore | C84: Asia | D84: 709.15 | F84: 18.75 | J84: 7.6 | K84: Singapore | Q84: Normal | R84: Moderate (6-8%)
A85: 2005 | B85: Singapore | C85: Asia | D85: 820.38 | F85: 22.13 | J85: 7.55 | K85: Singapore | Q85: Normal | R85: Moderate (6-8%)
A86: 2006 | B86: Singapore | C86: Asia | D86: 940.26 | F86: 28.33 | J86: 7.55 | K86: Singapore | Q86: Normal | R86: Moderate (6-8%)
A87: 2007 | B87: Singapore | C87: Asia | D87: 1217 | F87: 37.22 | J87: 7.56 | K87: Singapore | Q87: Normal | R87: Moderate (6-8%)
A88: 2008 | B88: Singapore | C88: Asia | D88: 1199 | F88: 49.98 | J88: 7.63 | K88: Singapore | Q88: Normal | R88: Moderate (6-8%)
A89: 2009 | B89: Singapore | C89: Asia | D89: 1342 | F89: 49.2 | J89: 7.64 | K89: Singapore | Q89: Normal | R89: Moderate (6-8%)
A90: 2010 | B90: Singapore | C90: Asia | D90: 1676 | F90: 53.48 | I90: 210000 | J90: 7.63 | K90: Singapore | O90: 254.66667 | P90: 210000 | Q90: Normal | R90: Moderate (6-8%)
A91: 2011 | B91: Singapore | C91: Asia | D91: 1823 | F91: 62.5 | J91: 7.61 | K91: Singapore | P91: 210000 | Q91: Normal | R91: Moderate (6-8%)
A92: 2012 | B92: Singapore | C92: Asia | D92: 1828 | F92: 68.82 | J92: 7.64 | K92: Singapore | P92: 210000 | Q92: Normal | R92: Moderate (6-8%)
A93: 2013 | B93: Singapore | C93: Asia | D93: 1857 | F93: 69.97 | J93: 7.68 | K93: Singapore | Q93: Normal | R93: Moderate (6-8%)
A94: 2014 | B94: Singapore | C94: Asia | D94: 2039 | F94: 70.39 | J94: 7.66 | K94: Singapore | Q94: Normal | R94: Moderate (6-8%)
A95: 2015 | B95: Singapore | C95: Asia | D95: 2104 | F95: 68.91 | I95: 310000 | J95: 7.63 | K95: Singapore | O95: 222.29032 | P95: 310000 | Q95: Normal | R95: Moderate (6-8%)
A96: 2016 | B96: Singapore | C96: Asia | D96: 2295 | F96: 62.74 | J96: 7.61 | K96: Singapore | P96: 310000 | Q96: Normal | R96: Moderate (6-8%)
A97: 2017 | B97: Singapore | C97: Asia | D97: 2651 | F97: 68.97 | J97: 7.63 | K97: Singapore | P97: 310000 | Q97: Normal | R97: Moderate (6-8%)
A98: 2018 | B98: Singapore | C98: Asia | D98: 2703 | F98: 78.79 | J98: 7.65 | K98: Singapore | Q98: Normal | R98: Moderate (6-8%)
A99: 2019 | B99: Singapore | C99: Asia | D99: 2836 | F99: 83.33 | J99: 6.51 | K99: Singapore | Q99: Normal | R99: Moderate (6-8%)
A100: 2020 | B100: Singapore | C100: Asia | D100: 2675 | F100: 83.15 | I100: 370000 | J100: 7.86 | K100: Singapore | O100: 224.72973 | P100: 370000 | Q100: High | R100: Moderate (6-8%)
...

Sheet Executive Insights
B2: Executive Insights
B3: 10 evidence-based findings, each with business impact and a recommendation.
B5: Insight | C5: What Happened | D5: Business Impact | E5: Recommendation
B6: 1. UAE is the largest single destination for Indian migrants | C6: As of 2024, the UAE hosts an estimated 3.25 million Indian migrants, the highest of the 7 countries tracked, narrowly ahead of the USA (3.17 million). | D6: The UAE corridor is disproportionately important to remittance flows and household income support in source states. | E6: Prioritize worker-protection agreements and skill-certification programs with the UAE given the scale of exposure.
B7: 2. Canada shows the fastest proportional growth of any tracked destination | C7: Canada's Indian migrant stock grew from 217,000 (2000) to 1.28 million (2024), a ~490% increase, the highest growth rate among all 7 countries. | D7: Canada has shifted from a minor destination to a top-3 corridor in two decades, driven by its points-based PR system and post-study work rights. | E7: Scale Canada-specific settlement and financial-literacy programs to match this growth.
B8: 3. The UK is the slowest-growing major destination | C8: UK migrant stock grew only ~70% between 2000 and 2024 (570,000 -> 970,000), far below every other tracked country. | D8: The UK's share of the total tracked Indian diaspora is shrinking relative to Canada, Australia, and the UAE, likely reflecting post-Brexit visa tightening. | E8: Flag the UK's comparatively constrained growth trajectory to prospective migrants against faster-expanding alternatives.
B9: 4. India's GDP grew 8.3x, but this coincided with rising, not falling, emigration | C9: India's GDP rose from $468B (2000) to $3.91T (2024) while migrant stock to these 7 destinations also rose sharply over the same period. | D9: Rising GDP alone is not a reliable predictor of reduced outward migration in this dataset - consistent with the globally observed 'migration hump.' | E9: Revisit policy framing that assumes GDP growth will organically curb migration.
B10: 5. Remittances grew over 10x, closely tracking GDP, not migrant headcount | C10: Remittances rose from $12.9B (2000) to $137.7B (2024), a ~10.7x increase, correlating strongly with India's GDP (r=0.98) and negatively with unemployment (r=-0.75). | D10: Remittance inflows are a resilient, expanding pillar of India's external finances, effectively decoupled from domestic unemployment cycles. | E10: Treat remittances as a structurally growing revenue stream; keep investing in low-cost remittance-channel infrastructure.
B11: 6. India's unemployment has been comparatively stable, with a 2020 spike and 2023 low | C11: Unemployment ranged narrowly between ~4.2% and ~7.9% across 2000-2024, spiking to 7.86% in 2020 and falling to a period-low 4.17% in 2023. | D11: Despite the 2020 shock, unemployment does not show a long-run deteriorating pattern over the 25-year window. | E11: Monitor the 2023 low for durability before treating it as a structural improvement.
B12: 7. UAE and Australia are the only countries where migrant stock declined between benchmarks | C12: The UAE's stock fell from 3.5M (2020) to 3.25M (2024), a rare contraction among tracked destinations. | D12: The UAE, while still the largest single destination, is the only tracked market showing net contraction risk, possibly tied to COVID-era return migration or labor localization policy. | E12: Treat the UAE corridor as maturing/plateauing rather than assuming continued high growth.
B13: 8. Workforce vs. student composition data is too sparse to generalize | C13: Only 2 of 182 country-year records have both Temporary Worker Share and Student Share populated (Australia 2020, UK 2024). | D13: Any dashboard claiming to show 'workforce vs. student migration trends' across all 7 countries would be showing mostly gaps, not signal. | E13: Flag this explicitly in any report using these fields; treat the 2 data points as anecdotes, not a trend.
B14: 9. GDP and Unemployment fields are national, not country-specific | C14: GDP_India and Unemployment_India repeat the same value across all 7 destination countries for a given year. | D14: Any correlation between these fields and a specific country's migrant stock reflects India-side conditions, not destination-country demand. | E14: Label these fields explicitly as 'India national indicator' to avoid misinterpretation.
B15: 10. Data completeness itself is a finding: 53% of raw cells are 'NOT AVAILABLE' | C15: Of 1,323 raw data cells, 703 (53.1%) are explicitly marked unavailable, concentrated in Permanent Migrants, Temporary Workers, and Students for most years. | D15: Any executive dashboard should surface data-completeness context rather than implying full annual coverage. | E15: Prioritize follow-up data sourcing for these sub-metrics if strategically important.

Sheet Data Quality Report
B2: Data Quality Report
B4: Issues Found (Before Cleaning)
B5: Source | C5: Raw_Data/indian_overseas_migration_dataset.csv - long format, one row per (Year, Destination Country, Metric).
B6: Total raw rows | C6: 1,323
B7: Exact duplicate rows | C7: 0
B8: Cells marked NOT AVAILABLE | C8: 703 (53.1% of all cells)
B9: Rows missing a cited source | C9: 703
B10: Mixed value formats found | C10: Plain numbers, percentages, and currency strings ($468.40B and $1.217T) all stored as text in one column.
B11: Reshape required | C11: Data was long-format (one metric per row); pivoted to one row per Year x Country for analysis.
B13: Missing Values After Reshaping (per column)
B14: Column | C14: Missing Count | D14: Missing %
B15: Year | C15: 0 | D15: 0.0%
B16: Destination Country | C16: 0 | D16: 0.0%
B17: Region | C17: 0 | D17: 0.0%
B18: GDP India USD Billion | C18: 7 | D18: 3.8%
B19: Permanent Migrants | C19: 164 | D19: 90.1%
B20: Remittance USD Billion | C20: 7 | D20: 3.8%
B21: Students | C21: 159 | D21: 87.4%
B22: Temporary Workers | C22: 170 | D22: 93.4%
B23: Total Indian Migrants | C23: 147 | D23: 80.8%
B24: Unemployment India | C24: 0 | D24: 0.0%
B25: Destination Country Full | C25: 0 | D25: 0.0%
B26: Migrant YoY Growth Pct | C26: 182 | D26: 100.0%
... B32: India Unemployment Category | C32: 0 | D32: 0.0%
B34: Key Data Limitations
B35: - Scope: only 7 destination countries are covered - a sample of major corridors, not a complete global picture.
B36: - Granularity: no Indian state-level, gender, age, or education breakdown exists in the source file.
B37: - Migrant-count data (Permanent/Temporary/Students) is sparse, especially pre-2010.
B38: - GDP_India and Unemployment_India are national figures, repeated across all 7 countries per year.
B39: - Years extend to 2026; the most recent 1-2 years may be projections rather than finalized statistics.

Sheet Data Dictionary
B2: Data Dictionary
B4: Column | C4: Description | D4: Source Coverage
B5: Year | C5: Calendar year of the record | D5: Full, 2000-2026
B6: Destination Country | C6: Short country name | D6: Full
B7: Destination Country Full | C7: Standardized full country name | D7: Full
B8: Region | C8: Geographic region of destination country | D8: Full
B9: Total Indian Migrants | C9: Estimated total stock of Indian-born migrants in that country | D9: Sparse - benchmark years only (2000, 2005/2010, 2015, 2020, 2024)
B10: Permanent Migrants | C10: Estimated permanent-resident migrants | D10: Very sparse
B11: Temporary Workers | C11: Estimated temporary/contract workers | D11: Very sparse
B12: Students | C12: Estimated Indian student population | D12: Very sparse
B13: Remittance USD Billion | C13: India-WIDE total remittances received (not country-specific) | D13: Near-full, 2000-2024
B14: Unemployment India | C14: India-WIDE national unemployment rate (%) | D14: Full
B15: GDP India USD Billion | C15: India-WIDE GDP in USD billions (normalized from mixed $B/$T source notation) | D15: Near-full, 2000-2024; 2025-2026 not yet available
... B22: India Unemployment Category | C22: Bucketed unemployment rate: Low (<6%), Moderate (6-8%), High (>8%) | D22: Derived
B25: Important Interpretation Notes
B26: - Remittance, Unemployment, and GDP fields are national (India-wide) figures, repeated identically across all 7 destination countries for a given year. Never sum them across countries.
B27: - Total Indian Migrants and its sub-categories are only available for benchmark years - any year-over-year growth spans multi-year gaps, not annual change.
B28: - All currency figures are normalized to USD Billions (source mixed $B and $T notation).
